messageflux/__init__.py
messageflux/base_service.py
messageflux/message_handling_service.py
messageflux/metadata_headers.py
messageflux/pipeline_service.py
messageflux/py.typed
messageflux/server_loop_service.py
messageflux/iodevices/__init__.py
messageflux/iodevices/base/__init__.py
messageflux/iodevices/base/common.py
messageflux/iodevices/base/input_devices.py
messageflux/iodevices/base/input_transaction.py
messageflux/iodevices/base/output_devices.py
messageflux/iodevices/collection_device_wrapper/__init__.py
messageflux/iodevices/collection_device_wrapper/collection_input_device.py
messageflux/iodevices/collection_device_wrapper/collection_output_device.py
messageflux/iodevices/failover_output_device_wrapper/__init__.py
messageflux/iodevices/failover_output_device_wrapper/failover_output_device.py
messageflux/iodevices/file_system/__init__.py
messageflux/iodevices/file_system/file_system_device_manager_base.py
messageflux/iodevices/file_system/file_system_input_device.py
messageflux/iodevices/file_system/file_system_output_device.py
messageflux/iodevices/file_system/file_system_serializer.py
messageflux/iodevices/in_memory_device/__init__.py
messageflux/iodevices/in_memory_device/in_memory_device_manager.py
messageflux/iodevices/message_store_device_wrapper/__init__.py
messageflux/iodevices/message_store_device_wrapper/file_system_message_store.py
messageflux/iodevices/message_store_device_wrapper/message_store_base.py
messageflux/iodevices/message_store_device_wrapper/message_store_input_device.py
messageflux/iodevices/message_store_device_wrapper/message_store_output_device.py
messageflux/iodevices/message_store_device_wrapper/message_store_transformer_base.py
messageflux/iodevices/objectstorage/__init__.py
messageflux/iodevices/objectstorage/s3_message_store.py
messageflux/iodevices/objectstorage/s3api/__init__.py
messageflux/iodevices/objectstorage/s3api/s3bucket.py
messageflux/iodevices/objectstorage/s3api/s3client.py
messageflux-0.5.7.dist-info/LICENSE
messageflux-0.5.7.dist-info/METADATA
messageflux-0.5.7.dist-info/WHEEL
messageflux-0.5.7.dist-info/top_level.txt
messageflux-0.5.7.dist-info/RECORD
