Metadata-Version: 2.1
Name: messageflux
Version: 0.5.7
Author-email: Aviv Salem <avivsalem@gmail.com>
Maintainer-email: Aviv Salem <avivsalem@gmail.com>, Nir Schulman <narsssx@gmail.com>, Rafael Zilberman <Zilberman.rafi@gmail.com>
License: MIT
Project-URL: Homepage, https://github.com/Avivsalem/MessageFlux/
Project-URL: Documentation, https://messageflux.readthedocs.io/
Platform: win32
Platform: linux
Classifier: Programming Language :: Python
Classifier: Programming Language :: Python :: 3.7
Classifier: Programming Language :: Python :: 3.8
Classifier: Programming Language :: Python :: 3.9
Classifier: Programming Language :: Python :: 3.10
Classifier: Programming Language :: Python :: 3.11
Classifier: License :: OSI Approved :: MIT License
Requires-Python: <3.12,>=3.7
License-File: LICENSE
Provides-Extra: all
Requires-Dist: boto3-stubs[s3] <2,>=1.25 ; extra == 'all'
Requires-Dist: boto3-stubs[sqs] <2,>=1.25 ; extra == 'all'
Requires-Dist: boto3 <2,>=1.25 ; extra == 'all'
Requires-Dist: flake8 ; extra == 'all'
Requires-Dist: lxml ; extra == 'all'
Requires-Dist: mock ; extra == 'all'
Requires-Dist: moto ; extra == 'all'
Requires-Dist: mypy ; extra == 'all'
Requires-Dist: pika <2.0,>=1.0 ; extra == 'all'
Requires-Dist: pytest ; extra == 'all'
Requires-Dist: pytest-cov ; extra == 'all'
Requires-Dist: tox ; extra == 'all'
Requires-Dist: types-pika ; extra == 'all'
Provides-Extra: dev
Requires-Dist: pytest ; extra == 'dev'
Requires-Dist: pytest-cov ; extra == 'dev'
Requires-Dist: mock ; extra == 'dev'
Requires-Dist: moto ; extra == 'dev'
Requires-Dist: mypy ; extra == 'dev'
Requires-Dist: lxml ; extra == 'dev'
Requires-Dist: flake8 ; extra == 'dev'
Requires-Dist: tox ; extra == 'dev'
Provides-Extra: objectstorage
Requires-Dist: boto3 <2,>=1.25 ; extra == 'objectstorage'
Provides-Extra: objectstorage_mypy
Requires-Dist: boto3 <2,>=1.25 ; extra == 'objectstorage_mypy'
Requires-Dist: boto3-stubs[s3] <2,>=1.25 ; extra == 'objectstorage_mypy'
Provides-Extra: rabbitmq
Requires-Dist: pika <2.0,>=1.0 ; extra == 'rabbitmq'
Provides-Extra: rabbitmq_mypy
Requires-Dist: pika <2.0,>=1.0 ; extra == 'rabbitmq_mypy'
Requires-Dist: types-pika ; extra == 'rabbitmq_mypy'
Provides-Extra: sqs
Requires-Dist: boto3 <2,>=1.25 ; extra == 'sqs'
Provides-Extra: sqs_mypy
Requires-Dist: boto3 <2,>=1.25 ; extra == 'sqs_mypy'
Requires-Dist: boto3-stubs[sqs] <2,>=1.25 ; extra == 'sqs_mypy'
